discocrash/__init__.py
discocrash/channels.py
discocrash/crash.py
discocrash/loghooks.py
discocrash/members.py
discocrash/perms.py
discocrash/spam.py
discocrash.py-0.1.1.dist-info/LICENSE
discocrash.py-0.1.1.dist-info/METADATA
discocrash.py-0.1.1.dist-info/WHEEL
discocrash.py-0.1.1.dist-info/top_level.txt
discocrash.py-0.1.1.dist-info/RECORD
