Metadata-Version: 2.1
Name: discocrash.py
Version: 0.1.1
Summary: Module for creating discord crash bots
Home-page: https://github.com/discocrash-py/discorash.py
Author: JanekDeveloper
Author-email: ivanbogynsky@gmail.com
Classifier: Programming Language :: Python :: 3.8
Classifier: Programming Language :: Python :: 3.9
Classifier: Programming Language :: Python :: 3.10
Classifier: License :: OSI Approved :: GNU General Public License v3 (GPLv3)
License-File: LICENSE
Requires-Dist: discord (==1.7.3)
Requires-Dist: requests (>=2)
